leap_labs_task/__init__.py
leap_labs_task/main.py
leap_labs_task/utils.py
leap_labs_task-0.1.4.dist-info/METADATA
leap_labs_task-0.1.4.dist-info/WHEEL
leap_labs_task-0.1.4.dist-info/RECORD
