Metadata-Version: 2.1
Name: leap-labs-task
Version: 0.1.4
Summary: Ahmed Shahin submission for leap labs task -- adversarial noise
Author: ahmedhshahin
Author-email: ahmed.shahin.19@ucl.ac.uk
Requires-Python: >=3.10,<4.0
Classifier: Programming Language :: Python :: 3
Classifier: Programming Language :: Python :: 3.10
Classifier: Programming Language :: Python :: 3.11
Classifier: Programming Language :: Python :: 3.12
Classifier: Programming Language :: Python :: 3.13
Requires-Dist: matplotlib (>=3.9.2,<4.0.0)
Requires-Dist: torch (>=2.5.1,<3.0.0)
Requires-Dist: torchvision (>=0.20.1,<0.21.0)
